code_engine_client/__init__.py
code_engine_client/bot_api_conn_grpc_pb2.py
code_engine_client/bot_api_conn_grpc_pb2_grpc.py
code_engine_client/code_engine_client.py
code_engine_client-1.0.1.dist-info/METADATA
code_engine_client-1.0.1.dist-info/WHEEL
code_engine_client-1.0.1.dist-info/top_level.txt
code_engine_client-1.0.1.dist-info/RECORD
